bbalg/__init__.py
bbalg/_version.py
bbalg/main.py
bbalg-1.0.2.dist-info/LICENSE
bbalg-1.0.2.dist-info/METADATA
bbalg-1.0.2.dist-info/WHEEL
bbalg-1.0.2.dist-info/top_level.txt
bbalg-1.0.2.dist-info/RECORD
