Metadata-Version: 2.1
Name: bbalg
Version: 1.0.2
Summary: Baba algorithm for robustly determining status changes of objects to be tracked.
Author-email: Katsuya Hyodo <rmsdh122@yahoo.co.jp>
License: MIT License
Project-URL: Homepage, https://github.com/PINTO0309/bbalg
Classifier: Programming Language :: Python :: 3
Requires-Python: >=3.10
License-File: LICENSE
